pyreadstore/__init__.py
pyreadstore/__version__.py
pyreadstore/pyreadstore.py
pyreadstore/rsclient.py
pyreadstore/rsdataclasses.py
pyreadstore/rsexceptions.py
pyreadstore-1.2.0.dist-info/LICENSE
pyreadstore-1.2.0.dist-info/METADATA
pyreadstore-1.2.0.dist-info/WHEEL
pyreadstore-1.2.0.dist-info/top_level.txt
pyreadstore-1.2.0.dist-info/RECORD
