Metadata-Version: 2.1
Name: pyreadstore
Version: 1.2.0
Summary: PyReadStore is the Python client (SDK) for the ReadStore API
Home-page: https://github.com/EvobyteDigitalBiology/pyreadstore
Author: Jonathan Alles
Author-email: Jonathan.Alles@evo-byte.com
License: Apache-2.0 license
Classifier: Programming Language :: Python :: 3
Classifier: License :: OSI Approved :: Apache Software License
Classifier: Operating System :: Unix
Requires-Python: >=3.10
License-File: LICENSE
Requires-Dist: requests>=2.32.3
Requires-Dist: pydantic>=2.10
Requires-Dist: pandas>=2.2
